MANIFEST.in
README.txt
setup.cfg
setup.py
medialog/.DS_Store
medialog/__init__.py
medialog.tablebehavior.egg-info/.DS_Store
medialog.tablebehavior.egg-info/PKG-INFO
medialog.tablebehavior.egg-info/SOURCES.txt
medialog.tablebehavior.egg-info/dependency_links.txt
medialog.tablebehavior.egg-info/entry_points.txt
medialog.tablebehavior.egg-info/namespace_packages.txt
medialog.tablebehavior.egg-info/not-zip-safe
medialog.tablebehavior.egg-info/requires.txt
medialog.tablebehavior.egg-info/top_level.txt
medialog/tablebehavior/.DS_Store
medialog/tablebehavior/__init__.py
medialog/tablebehavior/behavior.py
medialog/tablebehavior/behaviors.zcml
medialog/tablebehavior/configure.zcml
medialog/tablebehavior/browser/.DS_Store
medialog/tablebehavior/browser/__init__.py
medialog/tablebehavior/browser/configure.zcml
medialog/tablebehavior/browser/viewlet.pt
medialog/tablebehavior/browser/viewlet.py
medialog/tablebehavior/browser/static/.DS_Store
medialog/tablebehavior/browser/static/copy-60x60.png
medialog/tablebehavior/browser/static/css.css
medialog/tablebehavior/browser/static/css_002.css
medialog/tablebehavior/browser/static/cut-60x60.png
medialog/tablebehavior/browser/static/delete-col-60x60.png
medialog/tablebehavior/browser/static/delete-col-disabled-60x60.png
medialog/tablebehavior/browser/static/delete-row-60x60.png
medialog/tablebehavior/browser/static/delete-row-disabled-60x60.png
medialog/tablebehavior/browser/static/flextableedit.js
medialog/tablebehavior/browser/static/insert-col-60x60.png
medialog/tablebehavior/browser/static/insert-row-60x60.png
medialog/tablebehavior/browser/static/jquery.flextable kopi.js
medialog/tablebehavior/browser/static/jquery.flextableedit.js
medialog/tablebehavior/browser/static/jquery.js
medialog/tablebehavior/browser/static/menu-h-24x24.png
medialog/tablebehavior/browser/static/modernizr-2.js
medialog/tablebehavior/browser/static/paste-60x60.png
medialog/tablebehavior/browser/static/paste-disabled-60x60.png
medialog/tablebehavior/browser/static/responsive.css
medialog/tablebehavior/browser/static/service.css
medialog/tablebehavior/browser/static/service.flextabledit.jquery.css
medialog/tablebehavior/browser/static/service.flextabledit.jquery.js
medialog/tablebehavior/browser/static/service.flextabledit.jquery.min.js
medialog/tablebehavior/browser/static/service.js
medialog/tablebehavior/browser/static/service_002.css
