Metadata-Version: 1.1
Name: medialog.tablebehavior
Version: 0.1
Summary: tablebehavior for Plone
Home-page: http://github.com/espenmn/medialog.tablebehavior
Author: Espen Moe-Nilssen
Author-email: espen@medialog.no
License: GPL
Platform: UNKNOWN
Classifier: Framework :: Plone
Classifier: Framework :: Plone :: 5.0
Classifier: Programming Language :: Python
Classifier: Topic :: Software Development :: Libraries :: Python Modules
